LICENSE.md
README.md
pyproject.toml
src/esrf_pathlib/__init__.py
src/esrf_pathlib/core.py
src/esrf_pathlib.egg-info/PKG-INFO
src/esrf_pathlib.egg-info/SOURCES.txt
src/esrf_pathlib.egg-info/dependency_links.txt
src/esrf_pathlib.egg-info/requires.txt
src/esrf_pathlib.egg-info/top_level.txt
src/esrf_pathlib/schemas/__init__.py
src/esrf_pathlib/schemas/_base.py
src/esrf_pathlib/schemas/_esrf_v1.py
src/esrf_pathlib/schemas/_esrf_v2.py
src/esrf_pathlib/schemas/_esrf_v3.py
src/esrf_pathlib/schemas/_utils.py
src/esrf_pathlib/tests/__init__.py
src/esrf_pathlib/tests/test_core.py
src/esrf_pathlib/tests/utils.py