Metadata-Version: 2.4
Name: esrf-pathlib
Version: 0.3.0
Summary: A drop-in pathlib clone with ESRF-specific path utilities
Author-email: ESRF <dau-pydev@esrf.fr>
License: # MIT License
Project-URL: Homepage, https://gitlab.esrf.fr/workflow/esrf-pathlib
Project-URL: Documentation, https://esrf-pathlib.readthedocs.io/
Project-URL: Repository, https://gitlab.esrf.fr/workflow/esrf-pathlib
Project-URL: Issues, https://gitlab.esrf.fr/workflow/esrf-pathlib/issues
Project-URL: Changelog, https://gitlab.esrf.fr/workflow/esrf-pathlib/-/blob/main/CHANGELOG.md
Keywords: ESRF,pathlib
Classifier: Intended Audience :: Science/Research
Classifier: License :: OSI Approved :: MIT License
Classifier: Programming Language :: Python :: 3
Requires-Python: >=3.8
License-File: LICENSE.md
Provides-Extra: test
Requires-Dist: pytest>=7.0; extra == "test"
Provides-Extra: dev
Requires-Dist: esrf-pathlib[test]; extra == "dev"
Requires-Dist: black>=22; extra == "dev"
Requires-Dist: flake8>=4.0; extra == "dev"
Provides-Extra: doc
Requires-Dist: esrf-pathlib[test]; extra == "doc"
Requires-Dist: sphinx>=6.0; extra == "doc"
Requires-Dist: sphinx-autodoc-typehints; extra == "doc"
Requires-Dist: pydata-sphinx-theme; extra == "doc"
Dynamic: license-file
